flask_validictory.py
setup.py
Flask_Validictory.egg-info/PKG-INFO
Flask_Validictory.egg-info/SOURCES.txt
Flask_Validictory.egg-info/dependency_links.txt
Flask_Validictory.egg-info/not-zip-safe
Flask_Validictory.egg-info/requires.txt
Flask_Validictory.egg-info/top_level.txt