Metadata-Version: 1.1
Name: Flask-Validictory
Version: 0.1.0
Summary: Simple integration between Flask and Validictory.
Home-page: https://github.com/inner-loop/flask-validictory/
Author: Mark Angrish
Author-email: mark.angrish@innerloop.io
License: MIT
Platform: any
Classifier: Development Status :: 4 - Beta
Classifier: Environment :: Web Environment
Classifier: Intended Audience :: Developers
Classifier: License :: OSI Approved :: MIT License
Classifier: Operating System :: OS Independent
Classifier: Programming Language :: Python
Classifier: Topic :: Internet :: WWW/HTTP :: Dynamic Content
Classifier: Topic :: Software Development :: Libraries :: Python Modules
